animation/__init__.py
animation/animations.py
animation/decorators.py
animation-0.0.7.dist-info/LICENSE
animation-0.0.7.dist-info/METADATA
animation-0.0.7.dist-info/WHEEL
animation-0.0.7.dist-info/top_level.txt
animation-0.0.7.dist-info/RECORD
