Metadata-Version: 1.1
Name: animation
Version: 0.0.7
Summary: Decorators for terminal-based wait animations.
Home-page: https://github.com/bprinty/animation
Author: Blake Printy
Author-email: bprinty@gmail.com
License: MIT
Keywords: animation,wait,waiting,status
Platform: UNKNOWN
Classifier: Intended Audience :: Developers
Classifier: License :: OSI Approved :: Apple Public Source License
Classifier: Natural Language :: English
Classifier: Programming Language :: Python :: 2
Classifier: Programming Language :: Python :: 2.6
Classifier: Programming Language :: Python :: 2.7
Classifier: Programming Language :: Python :: 3
Classifier: Programming Language :: Python :: 3.3
Classifier: Programming Language :: Python :: 3.4
Classifier: Programming Language :: Python :: 3.5
Classifier: Programming Language :: Python :: 3.6
Classifier: Programming Language :: Python :: 3.7
